django_prices_vatlayer/__init__.py
django_prices_vatlayer/admin.py
django_prices_vatlayer/apps.py
django_prices_vatlayer/models.py
django_prices_vatlayer/utils.py
django_prices_vatlayer/management/__init__.py
django_prices_vatlayer/management/commands/__init__.py
django_prices_vatlayer/management/commands/get_vat_rates.py
django_prices_vatlayer/migrations/0001_initial.py
django_prices_vatlayer/migrations/0002_ratetypes.py
django_prices_vatlayer/migrations/0003_auto_20180316_1053.py
django_prices_vatlayer/migrations/__init__.py
django_prices_vatlayer-1.1.0.dist-info/LICENSE
django_prices_vatlayer-1.1.0.dist-info/METADATA
django_prices_vatlayer-1.1.0.dist-info/WHEEL
django_prices_vatlayer-1.1.0.dist-info/top_level.txt
django_prices_vatlayer-1.1.0.dist-info/RECORD
